ieeLabTools/__init__.py
ieeLabTools/core.py
ieelabtools-0.1.3.dist-info/METADATA
ieelabtools-0.1.3.dist-info/WHEEL
ieelabtools-0.1.3.dist-info/licenses/LICENSE
ieelabtools-0.1.3.dist-info/RECORD
