Metadata-Version: 2.4
Name: ieeLabTools
Version: 0.1.3
Summary: General linear symbolic + numeric uncertainty propagation, weighted linear regression
Project-URL: Homepage, https://github.com/ieepirzy/ieeLabTools
Project-URL: Documentation, https://github.com/ieepirzy/ieeLabTools/blob/main/Docs/Documentation.md
Project-URL: Source, https://github.com/ieepirzy/ieeLabTools/blob/main/Source/core.py
Author-email: Ilari Pirkkalainen <iladevv0@gmail.com>
License: MIT
License-File: LICENSE
Classifier: Intended Audience :: Education
Classifier: Intended Audience :: Science/Research
Classifier: License :: OSI Approved :: MIT License
Classifier: Programming Language :: Python :: 3
Classifier: Topic :: Scientific/Engineering
Requires-Python: >=3.9
Requires-Dist: numpy
Requires-Dist: sympy
